egyptian_phone_validator/__init__.py
egyptian_phone_validator/validators.py
egyptian_phone_validator/tests/__init__.py
egyptian_phone_validator/tests/test_validators.py
egyptian_phone_validator-0.1.1.dist-info/LICENSE
egyptian_phone_validator-0.1.1.dist-info/METADATA
egyptian_phone_validator-0.1.1.dist-info/WHEEL
egyptian_phone_validator-0.1.1.dist-info/top_level.txt
egyptian_phone_validator-0.1.1.dist-info/RECORD
