Metadata-Version: 2.2
Name: egyptian-phone-validator
Version: 0.1.1
Summary: A Django package to validate Egyptian phone numbers.
Home-page: https://github.com/Moataz0000/egyptian-phone-validator
Author: Moataz Fawzy
Author-email: motazfawzy73@gmail.com
Classifier: Framework :: Django
Classifier: Programming Language :: Python :: 3
Classifier: License :: OSI Approved :: MIT License
Classifier: Operating System :: OS Independent
Requires-Python: >=3.6
License-File: LICENSE
Requires-Dist: Django>=3.0
Dynamic: author
Dynamic: author-email
Dynamic: classifier
Dynamic: description
Dynamic: description-content-type
Dynamic: home-page
Dynamic: requires-dist
Dynamic: requires-python
Dynamic: summary
